mathwords/__init__.py
mathwords/__main__.py
mathwords/lexer.py
mathwords/two_way_dict.py
mathwords-0.0.1.dist-info/LICENSE
mathwords-0.0.1.dist-info/METADATA
mathwords-0.0.1.dist-info/WHEEL
mathwords-0.0.1.dist-info/top_level.txt
mathwords-0.0.1.dist-info/RECORD
