Metadata-Version: 2.1
Name: mathwords
Version: 0.0.1
Summary: A calculator that uses words
Home-page: https://gitlab.com/playfulpachyderm/mathwords
Author: playfulpachyderm
Author-email: playful.pachyderm@gmail.com
License: UNKNOWN
Platform: UNKNOWN
Classifier: Programming Language :: Python :: 3
Classifier: License :: OSI Approved :: MIT License
Classifier: Operating System :: OS Independent
